vali/__init__.py
vali/_version.py
vali/exception.py
vali/helper.py
vali/validation.py
vali/tests/test_helper.py
vali_helper-1.1.0.dist-info/LICENSE
vali_helper-1.1.0.dist-info/METADATA
vali_helper-1.1.0.dist-info/WHEEL
vali_helper-1.1.0.dist-info/top_level.txt
vali_helper-1.1.0.dist-info/RECORD
