Metadata-Version: 2.1
Name: vali-helper
Version: 1.1.0
Summary: vali-helper is a util to help define the value checker on a function.
Author-email: babybabycloud <babybabycloud2020@gmail.com>
License: MIT License
Project-URL: homepage, https://github.com/babybabycloud/vali-helper
Keywords: validation
Classifier: Programming Language :: Python
License-File: LICENSE
Provides-Extra: dateutil
Requires-Dist: python-dateutil ==2.9.0 ; extra == 'dateutil'
